matchbot/__init__.py
matchbot/demo.py
matchbot/databasemanager/__init__.py
matchbot/discordbot/__init__.py
matchbot/discordbot/usercog.py
matchbot/gameservermanager/__init__.py
matchbot/gameservermanager/gameserver.py
matchbot_dev-0.0.2.dist-info/LICENSE.txt
matchbot_dev-0.0.2.dist-info/METADATA
matchbot_dev-0.0.2.dist-info/WHEEL
matchbot_dev-0.0.2.dist-info/top_level.txt
matchbot_dev-0.0.2.dist-info/RECORD
