Metadata-Version: 2.1
Name: matchbot-dev
Version: 0.0.2
Summary: Start dedicated servers for CS:GO matches from a web app or Discord
Home-page: https://github.com/theo-brown/matchbot
Author: Theo Brown
Author-email: theo.brown.uk@gmail.com
License: GNU GPLv3
Platform: UNKNOWN
Classifier: Programming Language :: Python :: 3
License-File: LICENSE.txt
Requires-Dist: asyncio
Requires-Dist: aiorcon
Requires-Dist: aiodocker
Requires-Dist: aiopg
Requires-Dist: discord
